screwhashcounter/README.MD
screwhashcounter/__init__.py
screwhashcounter/requirements.txt
screwhashcounter/thirdparty.json
screwhashcounter-0.10.dist-info/LICENSE.rst
screwhashcounter-0.10.dist-info/METADATA
screwhashcounter-0.10.dist-info/WHEEL
screwhashcounter-0.10.dist-info/top_level.txt
screwhashcounter-0.10.dist-info/RECORD
