Metadata-Version: 2.1
Name: screwhashcounter
Version: 0.10
Summary: provides a convenient and efficient way to count the occurrences of items (hashable and unhashable)
Home-page: https://github.com/hansalemaos/screwhashcounter
Author: Johannes Fischer
Author-email: aulasparticularesdealemaosp@gmail.com
License: MIT
Keywords: Counter,hash,collections
Classifier: Development Status :: 4 - Beta
Classifier: Programming Language :: Python :: 3 :: Only
Classifier: Programming Language :: Python :: 3.10
Classifier: Topic :: Software Development :: Libraries :: Python Modules
Classifier: Topic :: Utilities
License-File: LICENSE.rst
